odoo8_addon_purchase_requisition_auto_rfq-8.0.0.2.0.99.dev5-py2.7-nspkg.pth
odoo8_addon_purchase_requisition_auto_rfq-8.0.0.2.0.99.dev5.dist-info/DESCRIPTION.rst
odoo8_addon_purchase_requisition_auto_rfq-8.0.0.2.0.99.dev5.dist-info/METADATA
odoo8_addon_purchase_requisition_auto_rfq-8.0.0.2.0.99.dev5.dist-info/RECORD
odoo8_addon_purchase_requisition_auto_rfq-8.0.0.2.0.99.dev5.dist-info/WHEEL
odoo8_addon_purchase_requisition_auto_rfq-8.0.0.2.0.99.dev5.dist-info/metadata.json
odoo8_addon_purchase_requisition_auto_rfq-8.0.0.2.0.99.dev5.dist-info/namespace_packages.txt
odoo8_addon_purchase_requisition_auto_rfq-8.0.0.2.0.99.dev5.dist-info/top_level.txt
odoo_addons/purchase_requisition_auto_rfq/__init__.py
odoo_addons/purchase_requisition_auto_rfq/__openerp__.py
odoo_addons/purchase_requisition_auto_rfq/demo/product_and_supplier.yml
odoo_addons/purchase_requisition_auto_rfq/i18n/fr.po
odoo_addons/purchase_requisition_auto_rfq/i18n/purchase_requisition_auto_rfq.pot
odoo_addons/purchase_requisition_auto_rfq/i18n/sl.po
odoo_addons/purchase_requisition_auto_rfq/model/__init__.py
odoo_addons/purchase_requisition_auto_rfq/model/purchase_requisition.py
odoo_addons/purchase_requisition_auto_rfq/static/description/icon.png
odoo_addons/purchase_requisition_auto_rfq/test/purchase_requisition.yml
odoo_addons/purchase_requisition_auto_rfq/test/purchase_requisition_no_supplier.yml
odoo_addons/purchase_requisition_auto_rfq/view/purchase_requisition.xml
