Metadata-Version: 2.0
Name: odoo8-addon-purchase-requisition-auto-rfq
Version: 8.0.0.2.0.99.dev5
Summary: Automatically create RFQ from a purchase requisition
Home-page: UNKNOWN
Author: Camptocamp,Odoo Community Association (OCA)
Author-email: support@odoo-community.org
License: AGPL-3
Platform: UNKNOWN
Classifier: Programming Language :: Python
Classifier: Framework :: Odoo
Classifier: License :: OSI Approved :: GNU Affero General Public License v3
Requires-Python: ~=2.7
Requires-Dist: odoo (<9.0a,>=8.0a)
